vyvoj25_fork/__init__.py
vyvoj25_fork/agents/__init__.py
vyvoj25_fork/agents/_exceptions.py
vyvoj25_fork/agents/inference_runner.py
vyvoj25_fork/agents/job.py
vyvoj25_fork/agents/jupyter.py
vyvoj25_fork/agents/log.py
vyvoj25_fork/agents/plugin.py
vyvoj25_fork/agents/py.typed
vyvoj25_fork/agents/types.py
vyvoj25_fork/agents/vad.py
vyvoj25_fork/agents/version.py
vyvoj25_fork/agents/worker.py
vyvoj25_fork/agents/beta/__init__.py
vyvoj25_fork/agents/beta/workflows/__init__.py
vyvoj25_fork/agents/beta/workflows/email_address.py
vyvoj25_fork/agents/cli/__init__.py
vyvoj25_fork/agents/cli/_run.py
vyvoj25_fork/agents/cli/cli.py
vyvoj25_fork/agents/cli/log.py
vyvoj25_fork/agents/cli/proto.py
vyvoj25_fork/agents/cli/watcher.py
vyvoj25_fork/agents/ipc/__init__.py
vyvoj25_fork/agents/ipc/channel.py
vyvoj25_fork/agents/ipc/inference_executor.py
vyvoj25_fork/agents/ipc/inference_proc_executor.py
vyvoj25_fork/agents/ipc/inference_proc_lazy_main.py
vyvoj25_fork/agents/ipc/job_executor.py
vyvoj25_fork/agents/ipc/job_proc_executor.py
vyvoj25_fork/agents/ipc/job_proc_lazy_main.py
vyvoj25_fork/agents/ipc/job_thread_executor.py
vyvoj25_fork/agents/ipc/log_queue.py
vyvoj25_fork/agents/ipc/mock_room.py
vyvoj25_fork/agents/ipc/proc_client.py
vyvoj25_fork/agents/ipc/proc_pool.py
vyvoj25_fork/agents/ipc/proto.py
vyvoj25_fork/agents/ipc/supervised_proc.py
vyvoj25_fork/agents/llm/__init__.py
vyvoj25_fork/agents/llm/_strict.py
vyvoj25_fork/agents/llm/chat_context.py
vyvoj25_fork/agents/llm/fallback_adapter.py
vyvoj25_fork/agents/llm/llm.py
vyvoj25_fork/agents/llm/mcp.py
vyvoj25_fork/agents/llm/realtime.py
vyvoj25_fork/agents/llm/remote_chat_context.py
vyvoj25_fork/agents/llm/tool_context.py
vyvoj25_fork/agents/llm/utils.py
vyvoj25_fork/agents/llm/_provider_format/__init__.py
vyvoj25_fork/agents/llm/_provider_format/anthropic.py
vyvoj25_fork/agents/llm/_provider_format/aws.py
vyvoj25_fork/agents/llm/_provider_format/google.py
vyvoj25_fork/agents/llm/_provider_format/mistralai.py
vyvoj25_fork-1.0.9.dist-info/METADATA
vyvoj25_fork-1.0.9.dist-info/WHEEL
vyvoj25_fork-1.0.9.dist-info/licenses/LICENSE
vyvoj25_fork-1.0.9.dist-info/RECORD
