Metadata-Version: 2.4
Name: vyvoj25-fork
Version: 1.0.9
Summary: Namespaced fork of LiveKit agents/plugins under 'vyvoj25_fork.*' to co-install with upstream.
Project-URL: Homepage, https://github.com/vyvoj25/livekit_agents_framework
Author: vyvoj25
License:                                  Apache License
License-File: LICENSE
Classifier: License :: OSI Approved :: Apache Software License
Classifier: Operating System :: OS Independent
Classifier: Programming Language :: Python :: 3
Requires-Python: >=3.10
Requires-Dist: aiohttp~=3.10
Requires-Dist: av>=14.0.0
Requires-Dist: click~=8.1
Requires-Dist: colorama>=0.4.6
Requires-Dist: docstring-parser>=0.16
Requires-Dist: eval-type-backport
Requires-Dist: livekit-api<2,>=1.0.4
Requires-Dist: livekit-blingfire~=1.0
Requires-Dist: livekit-protocol~=1.0
Requires-Dist: livekit<2,>=1.0.12
Requires-Dist: nest-asyncio>=1.6.0
Requires-Dist: numpy>=1.26.0
Requires-Dist: opentelemetry-api>=1.34
Requires-Dist: opentelemetry-exporter-otlp>=1.34.1
Requires-Dist: opentelemetry-sdk>=1.34.1
Requires-Dist: prometheus-client>=0.22
Requires-Dist: protobuf>=3
Requires-Dist: psutil>=7.0
Requires-Dist: pydantic<3,>=2.0
Requires-Dist: pyjwt>=2.0
Requires-Dist: sounddevice>=0.5
Requires-Dist: types-protobuf<5,>=4
Requires-Dist: typing-extensions>=4.12
Requires-Dist: watchfiles>=1.0
